coderflow/__init__.py
coderflow/cli.py
coderflow/agents/__init__.py
coderflow/agents/fastapi.py
coderflow/agents/react.py
coderflow/core/__init__.py
coderflow/core/agent.py
coderflow/core/parse.py
coderflow-0.0.1.dist-info/LICENSE.txt
coderflow-0.0.1.dist-info/METADATA
coderflow-0.0.1.dist-info/WHEEL
coderflow-0.0.1.dist-info/entry_points.txt
coderflow-0.0.1.dist-info/top_level.txt
coderflow-0.0.1.dist-info/RECORD
