Metadata-Version: 2.1
Name: coderflow
Version: 0.0.1
Summary: Stay in the flow while coding.
Author-email: Josh Tanke <josh@launchflow.com>
Requires-Python: >=3.10
License-File: LICENSE.txt
Requires-Dist: anthropic
Requires-Dist: keyring
Requires-Dist: rich
Requires-Dist: typer
